base64_regex/__init__.py
base64_regex/__init__.pyi
base64_regex/py.typed
base64_regex-0.1.2.dist-info/WHEEL
base64_regex-0.1.2.dist-info/METADATA
base64_regex-0.1.2.dist-info/RECORD
