Metadata-Version: 2.3
Name: base64-regex
Version: 0.1.2
Summary: Generate RegEx patterns for finding Base64 substrings
Author: Zeev Rotshtein
Author-email: Zeev Rotshtein <zeevro@gmail.com>
Requires-Python: >=3.10
Project-URL: Repository, https://github.com/zeevro/base64-regex
